[
    {
        "Data Source": "BIMP",
        "Model Name": "Linear Regression Baseline",
        "Best Test Loss": 0.5468761929834672,
        "MedAE": {
            "cost": 5327.6066015896795,
            "cycle_time": 1122.3227895389791,
            "waiting_time": 1588.9480857159579
        },
        "MAE": {
            "cost": 6876.897416774972,
            "cycle_time": 1951.3173543779342,
            "waiting_time": 2584.9852148162845
        },
        "MedAE_Percentage": {
            "cost": 15.934249236824927,
            "cycle_time": 6.282953918436323,
            "waiting_time": 4.615139434395179
        }
    },
    {
        "Data Source": "real",
        "Model Name": "Linear Regression Baseline",
        "Best Test Loss": 0.5101460386881471,
        "MedAE": {
            "cost": 9340.876884158584,
            "cycle_time": 4334.907142423119,
            "waiting_time": 4446.386160304273
        },
        "MAE": {
            "cost": 11250.74085470402,
            "cycle_time": 11545.069353865058,
            "waiting_time": 11809.490581874288
        },
        "MedAE_Percentage": {
            "cost": 12.738471561747222,
            "cycle_time": 15.100031925925897,
            "waiting_time": 18.88557567889014
        }
    },
    {
        "Data Source": "synthetic",
        "Model Name": "Linear Regression Baseline",
        "Best Test Loss": 0.38722680245885743,
        "MedAE": {
            "cost": 6771.503785937952,
            "cycle_time": 3908.9566016732897,
            "waiting_time": 3651.8532993317313
        },
        "MAE": {
            "cost": 9379.110745920198,
            "cycle_time": 12637.514306324834,
            "waiting_time": 12508.220136718379
        },
        "MedAE_Percentage": {
            "cost": 14.72172442081178,
            "cycle_time": 16.733114863201536,
            "waiting_time": 19.164120929381923
        }
    }
]